<annotation verified="yes">
  <folder>street-images</folder>
  <filename>1900_-75.186912_40.046807_0_338.30</filename>
  <path>/Users/divyachandana/Documents/NJIT/work/StreetView/street-images/1900_-75.186912_40.046807_0_338.30.jpg</path>
  <source>
    <database>Unknown</database>
  </source>
  <size>
    <width>1024</width>
    <height>768</height>
    <depth>3</depth>
  </size>
  <segmented>0</segmented>
  <object>
    <type>robndbox</type>
    <name>trunk</name>
    <pose>Unspecified</pose>
    <truncated>0</truncated>
    <difficult>0</difficult>
    <robndbox>
      <cx>767.885</cx>
      <cy>415.0464</cy>
      <w>60.7641</w>
      <h>179.664</h>
      <angle>0.07</angle>
    </robndbox>
  </object>
</annotation>
