<annotation verified="yes">
  <folder>street-images</folder>
  <filename>501_-75.219051_40.078071_0_10.32</filename>
  <path>/Users/divyachandana/Documents/NJIT/work/StreetView/street-images/501_-75.219051_40.078071_0_10.32.jpg</path>
  <source>
    <database>Unknown</database>
  </source>
  <size>
    <width>1024</width>
    <height>768</height>
    <depth>3</depth>
  </size>
  <segmented>0</segmented>
  <object>
    <type>robndbox</type>
    <name>trunk</name>
    <pose>Unspecified</pose>
    <truncated>0</truncated>
    <difficult>0</difficult>
    <robndbox>
      <cx>951.0575</cx>
      <cy>636.2529</cy>
      <w>14.0</w>
      <h>68.0</h>
      <angle>0.0</angle>
    </robndbox>
  </object>
  <object>
    <type>robndbox</type>
    <name>trunk</name>
    <pose>Unspecified</pose>
    <truncated>0</truncated>
    <difficult>0</difficult>
    <robndbox>
      <cx>355.5575</cx>
      <cy>541.2529</cy>
      <w>11.0</w>
      <h>46.0</h>
      <angle>0.0</angle>
    </robndbox>
  </object>
  <object>
    <type>robndbox</type>
    <name>trunk</name>
    <pose>Unspecified</pose>
    <truncated>0</truncated>
    <difficult>0</difficult>
    <robndbox>
      <cx>115.0575</cx>
      <cy>481.2529</cy>
      <w>10.0</w>
      <h>42.0</h>
      <angle>3.071593</angle>
    </robndbox>
  </object>
</annotation>
